README.md
setup.py
poker_game_runner/__init__.py
poker_game_runner/runner.py
poker_game_runner/state.py
poker_game_runner/utils.py
poker_game_runner.egg-info/PKG-INFO
poker_game_runner.egg-info/SOURCES.txt
poker_game_runner.egg-info/dependency_links.txt
poker_game_runner.egg-info/requires.txt
poker_game_runner.egg-info/top_level.txt
poker_game_runner/bots/__init__.py
poker_game_runner/bots/callBot.py
poker_game_runner/bots/example_bot.py
poker_game_runner/bots/foldBot.py
poker_game_runner/bots/randombot.py
poker_game_runner/bots/testBot.py