Metadata-Version: 1.1
Name: poker-game-runner
Version: 0.1.11
Summary: open_spiel poker tournament runner
Home-page: https://github.com/bovle/poker_game_runner.git
Author: Frederik Børsting
Author-email: frederik@live.dk
License: mit
Platform: UNKNOWN
Classifier: Development Status :: 3 - Alpha
Classifier: Intended Audience :: Other Audience
Classifier: License :: OSI Approved :: MIT License
Classifier: Operating System :: POSIX :: Linux
Classifier: Programming Language :: Python :: 3.8
